controller/controller.v
/**
 * control sequencer
 */

module controller (
    input i_debug, // design visiblity
    input i_clk, // clock signal
    input i_reset, // reset signal
    input [3:0] i_opcode, // opcode from instruction register
    input i_program_mode, // 0 == program mode, 1 == execution mode
    // control signals
    output o_program_counter_incr,
    output o_program_counter_enable,
    output o_mar_load,
    output o_ram_enable,
    output o_instruction_load,
    output o_instruction_send,
    output o_alu_subtract,
    output o_alu_send,
    output o_accumulator_load,
    output o_accumulator_send,
    output o_register_b_load,
    output o_register_out_load //
    );

    // opcodes
    reg[3:0] LDA = 4'b0000; // load the accumulator
    reg[3:0] ADD = 4'b0001; // add
    reg[3:0] SUB = 4'b0010; // subtract
    reg[3:0] OUT = 4'b1110; // output
    reg[3:0] HLT = 4'b1111; // halt

    // initialize control bits
    reg [11:0] control_bits = 12'b0000_0000_0000;

    assign o_program_counter_incr = control_bits[11];
    assign o_program_counter_enable = control_bits[10];
    assign o_mar_load = control_bits[9];
    assign o_ram_enable = control_bits[8];

    assign o_instruction_load = control_bits[7];
    assign o_instruction_send = control_bits[6];
    assign o_alu_subtract = control_bits[5];
    assign o_alu_send = control_bits[4];

    assign o_accumulator_load = control_bits[3];
    assign o_accumulator_send = control_bits[2];
    assign o_register_b_load = control_bits[1];
    assign o_register_out_load = control_bits[0];

    // "ring counter" 6 step counter
    integer step = 1;

    // halt flag to end execution
    reg halt = 0;

    always @(posedge i_clk or posedge i_reset) begin
        if (i_reset) begin
            //reset step back to 1
            step <= 1;
            //reset halt flag
            halt <= 0;
        end 

        // step cycle only when halt flag is not raised
        if (!halt) begin
            // fetch cycle step 1 
            if (step == 1) begin
                if (i_debug) $display("\nT1: address state");
                // enable program_counter
                // enable mar load
                control_bits <= 12'b0110_0000_0000;
                step <= step + 1;
            end

            // fetch cycle step 2
            else if (step == 2) begin
                if (i_debug) $display("T2: increment state");
                // program_incr
                control_bits <= 12'b1000_0000_0000; 
                step <= step + 1; 
            end

            // fetch cycle step 3
            else if (step == 3) begin
                if (i_debug) $display("T3: memory state");
                // enable ram
                // enable instruction load
                control_bits <= 12'b0001_1000_0000;
                step <= step + 1;
            end

            // instruction cycle 
            case (i_opcode)
                LDA: begin
                    case (step)
                        4: begin
                            if (i_debug) $display("T4: load MAR state");
                            // enable mar load
                            // enable intruction send
                            control_bits <= 12'b0010_0100_0000;
                            step <= step + 1;
                        end

                        5: begin
                            if (i_debug) $display("T5: load accumulator state");
                            // enable ram 
                            // enable accumulator load
                            control_bits <= 12'b0001_0000_1000;
                            step <= step + 1;
                        end

                        6: begin
                            if (i_debug) $display("T6: no op state");
                            control_bits <= 12'b0000_0000_0000;
                            step <= 1; // reset step counter
                        end
                    endcase
                end

                ADD, // ADD and SUB opcode perform same routine
                SUB: begin
                    case (step)
                        4: begin
                            if (i_debug) $display("T4: load MAR state");
                            // enable mar load
                            // enable intruction send
                            control_bits <= 12'b0010_0100_0000;
                            step <= step + 1;
                        end

                        5: begin
                            if (i_debug) $display("T5: load B register state");
                            // enable ram
                            // enable B register load
                            control_bits <= 12'b0001_0000_0010;
                            step <= step + 1;
                        end

                        6: begin 
                            // enable alu send and accumulator load

                            // subtract bit set low
                            if (i_opcode == ADD) begin
                                if (i_debug) $display("T6: add B to A state");
                                control_bits <= 12'b0000_0001_1000;
                            // subtract bit set high
                            end else begin
                                if (i_debug) $display("T6: subtract B from A state");
                                control_bits <= 12'b0000_0011_1000;
                            end
                            step <= 1; // reset step counter
                        end
                    endcase
                end

                OUT: begin
                    case (step)
                        4: begin
                            if (i_debug) $display("T4: load out register state");
                            // enable accumulator send
                            // enable out register load
                            control_bits <= 12'b0000_0000_0101;
                            step <= step + 1;
                        end

                        5: begin
                            if (i_debug) $display("T5: no op state");
                            control_bits <= 12'b0000_0000_0000;
                            step <= step + 1;
                        end

                        6: begin 
                            if (i_debug) $display("T6: no op state");
                            control_bits <= 12'b0000_0000_0000;
                            step <= 1; // reset step counter
                        end
                    endcase
                end

                HLT: begin
                    if (i_debug) $display("T4: halt state");  
                    control_bits <= 12'b0000_0000_0000;
                    halt = 1; // program is done, raise halt flag
                end

            endcase
        
        end

    end

    always @(i_opcode) begin
        if (i_debug) $display("\tnew opcode: %b", i_opcode);
    end

    /* debugging control sequence
    always @(control_bits) begin
        if (i_debug) $display("\tnew control sequence: %b", control_bits);
    end */

    // if program mode (0), halt flag is up
    // if execution mode (1), halt flag is down
    always @(i_program_mode) begin
        halt <= !i_program_mode;
    end

endmodule

register/register.v
/**
 * default 8-bit register with unbuffered output
 * used for B register and output register
 */

module register (
    input i_debug, // design visibility
    input i_reset, // reset register
    input i_load_enable, // load enable signal
    input [7:0] i_bus, // 8-bit input line
    output [7:0] o_unbuffered_out // unbuffered output to alu
);

    // initialize internal registers
    reg [7:0] data;

    assign o_unbuffered_out = data;

    // load values whenever bus is updated or load signal enabled
    always @(i_bus or posedge i_load_enable) begin
        if (i_load_enable) begin
            data <= i_bus;
            if (i_debug) $display("\tregister loaded: %b", i_bus);
        end
    end

    // reset values
    always @(posedge i_reset) begin
        data <= 8'bzzzzzzzz;
        if (i_debug) $display("\tregister reset: %b", 8'bzzzzzzzz);
    end

endmodule

accumulator/accumulator.v
/**
 * 8-bit accumulator
 */

module accumulator (
    input i_debug, // design visibility
    input i_reset, // reset register  
    input i_load_enable, // load enable signal
    input i_send_enable, // send enable signal
    input [7:0] i_bus, // 8-bit input line
    output [7:0] o_bus, // 8-bit output line
    output [7:0] o_unbuffered_out // unbuffered output
);

    // initialize values
    reg [7:0] data;

    // if send enable signal is low assign data to floating values
    assign o_bus = i_send_enable ? data : 8'bzzzzzzzz;
    assign o_unbuffered_out = data;
    

    // load values whenever bus is updated or load signal enabled
    always @(i_bus or posedge i_load_enable) begin
        if (i_load_enable) begin
            data <= i_bus;
            if (i_debug) $display("\taccumulator loaded: %b", i_bus);
        end
    end

    // reset values
    always @(posedge i_reset) begin
        data <= 8'bzzzzzzzz;
        if (i_debug) $display("\taccumulator reset: %b", 8'bzzzzzzzz);
    end

 endmodule

alu/alu.v
/**
 * 8-bit arithmetic logic unit
 * adder or subtractor using 2's complement
 */

module alu (
    input [7:0] i_a, // 8-bit value from accumulator
    input [7:0] i_b, // 8-bit value from b register
    input i_subtract, // 1 = subtract mode, 0 = add mode
    input i_send_enable, // send enable signal
    output [7:0] o_bus // 8-bit output
 );

    // initialization for internal registers
    reg [7:0] result;

    assign o_bus = i_send_enable ? result : 8'bzzzzzzzz;

    always @(posedge i_send_enable) begin
        // add or subtract depending on mode
        result = i_subtract ? (i_a - i_b) : (i_a + i_b);
    end
    
 endmodule

instruction_register/instruction_register.v
/**
 * instruction register with two 4-bit registers,
 * opcode register and address register
 */
 
module instruction_register (
    input i_debug, // design visibility
    input i_reset, // reset register 
    input i_load_enable, // load enable signal
    input i_send_enable, // send enable signal
    input [7:0] i_bus, // 8-bit instruction set
    output [3:0] o_opcode, // 4-bit opcode unbuffered output
    output [3:0] o_address // 4-bit address output
);

    // initialization for internal registers
    reg [3:0] opcode;
    reg [3:0] address;

    // if send enable signal low assign address to floating values
    assign o_opcode = opcode; //unbuffered output to controller
    assign o_address = i_send_enable ? address : 4'bzzzz;

    // load values whenever bus is updated or load signal enabled
    always @(i_bus or posedge i_load_enable) begin
        if (i_load_enable) begin
            opcode = i_bus[7:4];
            address = i_bus[3:0];
            if (i_debug) $display("\tIR loaded: %b", i_bus);
        end
    end

    // reset values
    always @(posedge i_reset) begin
        opcode <= 4'b0000;
        address <= 4'b0000;
      if (i_debug) $display("\tIR reset: %b", 8'b00000000);
   end

endmodule

ram_16x8/ram_16x8.v
/**
 * 16x8 RAM 
 */

module ram_16x8 (
    input i_debug, // design visibility
    input i_program_mode, // 0 == program mode, 1 == execution mode
    input [7:0] i_program_data, // data programmed before execution
    input [3:0] i_address, // address to read / write
    input i_enable, // enable signal
    output [7:0] o_bus // 8-bit output to main bus
);

    // internal registers
    reg [7:0] ram[0:15];

    // if read enable low assign output to floating values
    assign o_bus = i_enable ? ram[i_address] : 8'bzzzzzzzz;

    // only 16B of memory to simplify 
    // initialize every address of RAM with dont cares
    integer index;
    initial begin
        for(index = 0; index < 16; index=index+1) begin
            ram[index] = 8'bxxxxxxxx;
        end
    end

    // whenever address is updated
    always @(i_address) begin
        // if program mode is 0, write to address data from program_data bus
        if (!i_program_mode) begin
            ram[i_address] <= i_program_data;  
            if (i_debug) $display("\tRAM address: %b programmed with: %b",i_address, i_program_data);
        end
    end

    // whenever ram enable signal is high
    always @(posedge i_enable) begin
        if (i_debug) $display("\tRAM address: %b data to bus: %b",i_address, ram[i_address]);
    end

endmodule

mux_2x4/mux_2x4.v
/**
 * 4-bit multiplexer
 */

module mux_2x4 (
    input [3:0] i_address_a, // option 1 execution mode
    input [3:0] i_address_b, // option 0 program mode
    input i_select, // select signal
    output [3:0] o_address // selected result
);

    assign o_address = i_select ? i_address_a : i_address_b;

endmodule

memory_address_register/memory_address_register.v
/**
 * 4-bit memory address register
 */

module memory_address_register (
    input i_debug, // design visiblity
    input i_reset, // reset count to 0000
    input i_load_enable, // load enable signal
    input [3:0] i_address, // 4-bit address input
    output [3:0] o_address // 4-bit address output
);

    // initialization for internal register
    reg [3:0] address = 4'b0000;
    assign o_address = address;

    // load values whenever load signal enabled
    always @(i_address or posedge i_load_enable) begin
        if (i_load_enable) begin
            address <= i_address;
            if (i_debug) $display("\tMAR loaded: %b", i_address);
        end
    end

    //reset values
    always @(posedge i_reset) begin
        address = 4'b0000;
        if (i_debug) $display("\tMAR reset: %b", 4'b0000);
    end

endmodule

program_counter/program_counter.v
/**
 * program counter that counters from 0000 to 1111 then loops
 */

module program_counter (
    input i_debug, // design visiblity
    input i_reset, // reset count to 0000
    input i_incr, // increments on pos incr signal
    input i_enable, //tri-state output
    output [3:0] o_count // 4 bit output to 8 bit 
);

    // intialize internal registers
    reg[3:0] counter = 4'b0000;
    reg[7:0] counter_buffer = 4'bzzzz;
    assign o_count = counter_buffer;

    // increment counter
    always @ (posedge i_incr) begin
        // if counter reaches 1111 then reset, otherwise plus 1
        counter <= ((counter == 4'b1111) ? 4'b0000 : counter + 4'b0001);
        // pc seems to output debug message before increment occurs
        if (i_debug) $display("\tPC value incremented: %b", counter + 4'b0001);
    end 

    // output 
    always @ (i_enable) begin
        if (i_enable) begin
            counter_buffer <= counter;
            if (i_debug) $display("\tPC output to bus: %b", counter);
        end else begin
            counter_buffer <= 4'bzzzz;
        end
    end

    // reset
    always @ (posedge i_reset) begin
        counter <= 4'b0000;
        if (i_debug) $display("\tPC reset: %b", counter);
    end

endmodule

SAP.v
/** 
 * SAP-1 Computer simulated in Verilog
 */

`include "accumulator/accumulator.v"
`include "alu/alu.v"
`include "controller/controller.v"
`include "instruction_register/instruction_register.v"
`include "memory_address_register/memory_address_register.v"
`include "mux_2x4/mux_2x4.v"
`include "program_counter/program_counter.v"
`include "ram_16x8/ram_16x8.v"
`include "register/register.v"

module sap (
    input i_debug, // 1 debug flag for all modules for simplicity
    input i_clk, // clock signal
    input i_reset, // send reset signal before every run
    input i_program_mode, // 0 == program mode, 1 == execution mode
    input [7:0] i_program_data, // data to program
    input [3:0] i_program_address, // address to program to
    output [7:0] o_display // can be sent to seven segment display 
);

    // initialize controller signal bits
    wire program_counter_incr;
    wire program_counter_enable;
    wire mar_load;
    wire ram_enable;
    wire instruction_load;
    wire instruction_send;
    wire alu_subtract;
    wire alu_send;
    wire accumulator_load;
    wire accumulator_send;
    wire register_b_load;
    wire register_out_load;

    // initialize main components and connectors
    wire [7:0] bus; // main 8-bit bus 
    wire [3:0] opcode; // connects IR to controller
    wire [7:0] alu_a_in; // connects accumulator to alu
    wire [7:0] alu_b_in; // connects B register to alu
    wire [3:0] mar_to_mux; // connects mar to mux 
    wire [3:0] mux_to_ram; // connects mux to ram 

    // initialize modules
    program_counter pc (
        .i_debug(i_debug), 
        .i_reset(i_reset), 
        .i_incr(program_counter_incr), 
        .i_enable(program_counter_enable),
        .o_count(bus[3:0])
    );

    memory_address_register mar (
        .i_debug(i_debug),
        .i_reset(i_reset),
        .i_load_enable(mar_load),
        .i_address(bus[3:0]),
        .o_address(mar_to_mux)
    );  

    mux_2x4 mux (
        .i_address_a(mar_to_mux),
        .i_address_b(i_program_address),
        .i_select(i_program_mode),
        .o_address(mux_to_ram)
    );

    ram_16x8 ram (
        .i_debug(i_debug),
        .i_program_mode(i_program_mode),
        .i_program_data(i_program_data),
        .i_address(mux_to_ram),
        .i_enable(ram_enable),
        .o_bus(bus)
    );

    instruction_register ir (
        .i_debug(i_debug),
        .i_reset(i_reset),
        .i_load_enable(instruction_load),
        .i_send_enable(instruction_send),
        .i_bus(bus[7:0]),
        .o_opcode(opcode),
        .o_address(bus[3:0]) // bus[3:0]
    );

    alu adder_subtracter (
        .i_a(alu_a_in),
        .i_b(alu_b_in),
        .i_subtract(alu_substract),
        .i_send_enable(alu_send),
        .o_bus(bus)
    );

    accumulator acc (
        .i_debug(i_debug),
        .i_reset(i_reset),
        .i_load_enable(accumulator_load),
        .i_send_enable(accumulator_send),
        .i_bus(bus), 
        .o_bus(bus), 
        .o_unbuffered_out(alu_a_in)
    );

    register buffer (
        .i_debug(i_debug),
        .i_reset(i_reset),
        .i_load_enable(register_b_load),
        .i_bus(bus),
        .o_unbuffered_out(alu_b_in)
    );

    register out (
        .i_debug(i_debug),
        .i_reset(i_reset),
        .i_load_enable(register_out_load),
        .i_bus(bus),
        .o_unbuffered_out(o_display)
    );

    controller control (
        .i_debug(i_debug),
        .i_clk(i_clk),
        .i_reset(i_reset),
        .i_opcode(opcode),
        .i_program_mode(i_program_mode),
        .o_program_counter_incr(program_counter_incr),
        .o_program_counter_enable(program_counter_enable),
        .o_mar_load(mar_load),
        .o_ram_enable(ram_enable),
        .o_instruction_load(instruction_load),
        .o_instruction_send(instruction_send),
        .o_alu_subtract(alu_substract),
        .o_alu_send(alu_send),
        .o_accumulator_load(accumulator_load),
        .o_accumulator_send(accumulator_send),
        .o_register_b_load(register_b_load),
        .o_register_out_load(register_out_load)
    );

    always @(posedge i_reset) begin
        if (i_debug) $display ("\nsystem reset:");
    end

    // reads bus contents
    always @(bus) begin
        if (i_debug) $display("\tbus updated: %b", bus);
    end

    // reads output of computer
    always @(o_display) begin
        $display("\toutput register displays: %b", o_display);
    end

endmodule

SAP_test.v
/**
 * SAP-1 test file
 */

 `timescale 1ns / 1ns
 `include "SAP.v"

 module sap_test();

    //debug messages are a look inconsistent due to timing
    // but end result is correct
    reg debug = 1'b1; 
    reg clk;
    reg reset;
    reg program_mode;
    reg [7:0] program_data;
    reg [3:0] program_address;
    wire [7:0] display;

    sap computer (
        debug,
        clk,
        reset,
        program_mode,
        program_data,
        program_address,
        display
    );

    initial begin
        clk = 0;
        forever begin
            #5 clk = ~clk;
        end
    end

    initial begin

        // dump file to view in gtkwave simulator
        $dumpfile("test.vcd");
        $dumpvars;

        // program instructions before execution
        program_mode = 0; #10;

        // LDA 9H
        program_data = 8'b0000_1001; program_address = 4'b0000; #10;
        // ADD AH
        program_data = 8'b0001_1010; program_address = 4'b0001; #10;
        // ADD BH
        program_data = 8'b0001_1011; program_address = 4'b0010; #10;
        // SUB CH
        program_data = 8'b0010_1100; program_address = 4'b0011; #10;
        // OUT
        program_data = 8'b1110_xxxx; program_address = 4'b0100; #10;
        // HLT
        program_data = 8'b1111_xxxx; program_address = 4'b0101; #10;
        // 9H - 14
        program_data = 8'b0000_1110; program_address = 4'b1001; #10;
        // AH - 21
        program_data = 8'b0001_0101; program_address = 4'b1010; #10;
        // BH - 1 
        program_data = 8'b0000_0001; program_address = 4'b1011; #10;
        // CH - 7
        program_data = 8'b0000_0111; program_address = 4'b1100; #10;

        // start every run with a reset
        reset = 1; #10;
        reset = 0; #10;

        // execution
        program_mode = 1; #5; 
        #10; #10; #10; #10; #10; #10; #10; #10; #10; #10; #10; #10; 
        #10; #10; #10; #10; #10; #10; #10; #10; #10; #10; #10; #10; 
        #10; #10; #10; #10; #10; #10; #10; #10; #10; #10; #10; #10; 
        #10; #10; #10; #10; #10; #10; #10; #10; #10; #10; #10; #10; 
        #10; #10; #10; #10; #10; #10; #10; #10; #10; #10; #10; #10; 

        $finish;
    end

 endmodule

test.vcd
$date
	Tue Sep 22 00:00:06 2020
$end
$version
	Icarus Verilog
$end
$timescale
	1ns
$end
$scope module sap_test $end
$var wire 8 ! display [7:0] $end
$var reg 1 " clk $end
$var reg 1 # debug $end
$var reg 4 $ program_address [3:0] $end
$var reg 8 % program_data [7:0] $end
$var reg 1 & program_mode $end
$var reg 1 ' reset $end
$scope module computer $end
$var wire 8 ( bus [7:0] $end
$var wire 1 " i_clk $end
$var wire 1 # i_debug $end
$var wire 4 ) i_program_address [3:0] $end
$var wire 8 * i_program_data [7:0] $end
$var wire 1 & i_program_mode $end
$var wire 1 ' i_reset $end
$var wire 1 + register_out_load $end
$var wire 1 , register_b_load $end
$var wire 1 - ram_enable $end
$var wire 1 . program_counter_incr $end
$var wire 1 / program_counter_enable $end
$var wire 4 0 opcode [3:0] $end
$var wire 8 1 o_display [7:0] $end
$var wire 4 2 mux_to_ram [3:0] $end
$var wire 4 3 mar_to_mux [3:0] $end
$var wire 1 4 mar_load $end
$var wire 1 5 instruction_send $end
$var wire 1 6 instruction_load $end
$var wire 1 7 alu_substract $end
$var wire 1 8 alu_send $end
$var wire 8 9 alu_b_in [7:0] $end
$var wire 8 : alu_a_in [7:0] $end
$var wire 1 ; accumulator_send $end
$var wire 1 < accumulator_load $end
$scope module acc $end
$var wire 8 = i_bus [7:0] $end
$var wire 1 # i_debug $end
$var wire 1 ' i_reset $end
$var wire 8 > o_bus [7:0] $end
$var wire 8 ? o_unbuffered_out [7:0] $end
$var wire 1 ; i_send_enable $end
$var wire 1 < i_load_enable $end
$var reg 8 @ data [7:0] $end
$upscope $end
$scope module adder_subtracter $end
$var wire 8 A i_a [7:0] $end
$var wire 8 B o_bus [7:0] $end
$var wire 1 7 i_subtract $end
$var wire 1 8 i_send_enable $end
$var wire 8 C i_b [7:0] $end
$var reg 8 D result [7:0] $end
$upscope $end
$scope module buffer $end
$var wire 8 E i_bus [7:0] $end
$var wire 1 # i_debug $end
$var wire 1 ' i_reset $end
$var wire 8 F o_unbuffered_out [7:0] $end
$var wire 1 , i_load_enable $end
$var reg 8 G data [7:0] $end
$upscope $end
$scope module control $end
$var wire 1 " i_clk $end
$var wire 1 # i_debug $end
$var wire 1 & i_program_mode $end
$var wire 1 ' i_reset $end
$var wire 1 + o_register_out_load $end
$var wire 1 , o_register_b_load $end
$var wire 1 - o_ram_enable $end
$var wire 1 . o_program_counter_incr $end
$var wire 1 / o_program_counter_enable $end
$var wire 1 4 o_mar_load $end
$var wire 1 5 o_instruction_send $end
$var wire 1 6 o_instruction_load $end
$var wire 1 7 o_alu_subtract $end
$var wire 1 8 o_alu_send $end
$var wire 1 ; o_accumulator_send $end
$var wire 1 < o_accumulator_load $end
$var wire 4 H i_opcode [3:0] $end
$var reg 4 I ADD [3:0] $end
$var reg 4 J HLT [3:0] $end
$var reg 4 K LDA [3:0] $end
$var reg 4 L OUT [3:0] $end
$var reg 4 M SUB [3:0] $end
$var reg 12 N control_bits [11:0] $end
$var reg 1 O halt $end
$var integer 32 P step [31:0] $end
$upscope $end
$scope module ir $end
$var wire 8 Q i_bus [7:0] $end
$var wire 1 # i_debug $end
$var wire 1 6 i_load_enable $end
$var wire 1 ' i_reset $end
$var wire 1 5 i_send_enable $end
$var wire 4 R o_opcode [3:0] $end
$var wire 4 S o_address [3:0] $end
$var reg 4 T address [3:0] $end
$var reg 4 U opcode [3:0] $end
$upscope $end
$scope module mar $end
$var wire 4 V i_address [3:0] $end
$var wire 1 # i_debug $end
$var wire 1 4 i_load_enable $end
$var wire 1 ' i_reset $end
$var wire 4 W o_address [3:0] $end
$var reg 4 X address [3:0] $end
$upscope $end
$scope module mux $end
$var wire 4 Y i_address_a [3:0] $end
$var wire 4 Z i_address_b [3:0] $end
$var wire 1 & i_select $end
$var wire 4 [ o_address [3:0] $end
$upscope $end
$scope module out $end
$var wire 8 \ i_bus [7:0] $end
$var wire 1 # i_debug $end
$var wire 1 + i_load_enable $end
$var wire 1 ' i_reset $end
$var wire 8 ] o_unbuffered_out [7:0] $end
$var reg 8 ^ data [7:0] $end
$upscope $end
$scope module pc $end
$var wire 1 # i_debug $end
$var wire 1 / i_enable $end
$var wire 1 . i_incr $end
$var wire 1 ' i_reset $end
$var wire 4 _ o_count [3:0] $end
$var reg 4 ` counter [3:0] $end
$var reg 8 a counter_buffer [7:0] $end
$upscope $end
$scope module ram $end
$var wire 4 b i_address [3:0] $end
$var wire 1 # i_debug $end
$var wire 1 - i_enable $end
$var wire 8 c i_program_data [7:0] $end
$var wire 1 & i_program_mode $end
$var wire 8 d o_bus [7:0] $end
$var integer 32 e index [31:0] $end
$upscope $end
$upscope $end
$upscope $end
$enddefinitions $end
#0
$dumpvars
b10000 e
bz d
bx c
bx b
b0zzzz a
b0 `
bz _
bx ^
bx ]
bz \
bx [
bx Z
b0 Y
b0 X
b0 W
bz V
bx U
bx T
bz S
bx R
bz Q
b1 P
1O
b0 N
b10 M
b1110 L
b0 K
b1111 J
b1 I
bx H
bx G
bx F
bz E
bx D
bx C
bz B
bx A
bx @
bx ?
bz >
bz =
0<
0;
bx :
bx 9
08
07
06
05
04
b0 3
bx 2
bx 1
bx 0
0/
0.
0-
0,
0+
bx *
bx )
bz (
x'
0&
bx %
bx $
1#
0"
bx !
$end
#5
1"
#10
b0 2
b0 [
b0 b
0"
b0 $
b0 )
b0 Z
b1001 %
b1001 *
b1001 c
#15
1"
#20
b1 2
b1 [
b1 b
0"
b1 $
b1 )
b1 Z
b11010 %
b11010 *
b11010 c
#25
1"
#30
b10 2
b10 [
b10 b
0"
b10 $
b10 )
b10 Z
b11011 %
b11011 *
b11011 c
#35
1"
#40
b11 2
b11 [
b11 b
0"
b11 $
b11 )
b11 Z
b101100 %
b101100 *
b101100 c
#45
1"
#50
b100 2
b100 [
b100 b
0"
b100 $
b100 )
b100 Z
b1110xxxx %
b1110xxxx *
b1110xxxx c
#55
1"
#60
b101 2
b101 [
b101 b
0"
b101 $
b101 )
b101 Z
b1111xxxx %
b1111xxxx *
b1111xxxx c
#65
1"
#70
b1001 2
b1001 [
b1001 b
0"
b1001 $
b1001 )
b1001 Z
b1110 %
b1110 *
b1110 c
#75
1"
#80
b1010 2
b1010 [
b1010 b
0"
b1010 $
b1010 )
b1010 Z
b10101 %
b10101 *
b10101 c
#85
1"
#90
b1011 2
b1011 [
b1011 b
0"
b1011 $
b1011 )
b1011 Z
b1 %
b1 *
b1 c
#95
1"
#100
b1100 2
b1100 [
b1100 b
0"
b1100 $
b1100 )
b1100 Z
b111 %
b111 *
b111 c
#105
1"
#110
b0 T
b0 0
b0 H
b0 R
b0 U
bz :
bz ?
bz A
bz @
bz 9
bz C
bz F
bz G
bz !
bz 1
bz ]
bz ^
0O
0"
1'
#115
b0 V
bz0000 (
bz0000 =
bz0000 >
bz0000 B
bz0000 E
bz0000 Q
bz0000 \
bz0000 d
b0 _
b0 a
b0 3
b0 W
b0 X
b0 Y
1/
14
b10 P
b11000000000 N
1"
#120
0"
0'
#125
bz V
bz (
bz =
bz >
bz B
bz E
bz Q
bz \
bz d
bz _
b1 `
b0zzzz a
1.
0/
04
b11 P
b100000000000 N
1"
#130
b0 2
b0 [
b0 b
0"
1&
#135
b1001 V
b1001 (
b1001 =
b1001 >
b1001 B
b1001 E
b1001 Q
b1001 \
b1001 d
b1001 T
b0 0
b0 H
b0 R
b0 U
0.
1-
16
b100 P
b110000000 N
1"
#140
0"
#145
b1001 2
b1001 [
b1001 b
b1001 3
b1001 W
b1001 X
b1001 Y
bz1001 (
bz1001 =
bz1001 >
bz1001 B
bz1001 E
bz1001 Q
bz1001 \
bz1001 d
b1001 S
14
0-
06
15
b101 P
b1001000000 N
1"
#150
0"
#155
b1110 :
b1110 ?
b1110 A
b1110 @
b1110 V
b1110 (
b1110 =
b1110 >
b1110 B
b1110 E
b1110 Q
b1110 \
b1110 d
bz S
04
1-
05
1<
b110 P
b100001000 N
1"
#160
0"
#165
bz V
bz (
bz =
bz >
bz B
bz E
bz Q
bz \
bz d
0-
0<
b1 P
b0 N
1"
#170
0"
#175
b1 V
bz0001 (
bz0001 =
bz0001 >
bz0001 B
bz0001 E
bz0001 Q
bz0001 \
bz0001 d
b1 _
b1 2
b1 [
b1 b
b1 a
b1 3
b1 W
b1 X
b1 Y
1/
14
b10 P
b11000000000 N
1"
#180
0"
#185
bz V
bz (
bz =
bz >
bz B
bz E
bz Q
bz \
bz d
bz _
b10 `
b0zzzz a
1.
0/
04
b11 P
b100000000000 N
1"
#190
0"
#195
b1010 V
b11010 (
b11010 =
b11010 >
b11010 B
b11010 E
b11010 Q
b11010 \
b11010 d
b1010 T
b1 0
b1 H
b1 R
b1 U
0.
1-
16
b100 P
b110000000 N
1"
#200
0"
#205
b1010 2
b1010 [
b1010 b
b1010 3
b1010 W
b1010 X
b1010 Y
bz1010 (
bz1010 =
bz1010 >
bz1010 B
bz1010 E
bz1010 Q
bz1010 \
bz1010 d
b1010 S
14
0-
06
15
b101 P
b1001000000 N
1"
#210
0"
#215
b10101 9
b10101 C
b10101 F
b10101 G
b101 V
b10101 (
b10101 =
b10101 >
b10101 B
b10101 E
b10101 Q
b10101 \
b10101 d
bz S
04
1-
05
1,
b110 P
b100000010 N
1"
#220
0"
#225
b100011 :
b100011 ?
b100011 A
b100011 @
b11 V
b100011 (
b100011 =
b100011 >
b100011 B
b100011 E
b100011 Q
b100011 \
b100011 d
b100011 D
0-
18
1<
0,
b1 P
b11000 N
1"
#230
0"
#235
b10 _
b10 2
b10 [
b10 b
b10 a
b10 3
b10 W
b10 X
b10 Y
b10 V
bz0010 (
bz0010 =
bz0010 >
bz0010 B
bz0010 E
bz0010 Q
bz0010 \
bz0010 d
1/
14
08
0<
b10 P
b11000000000 N
1"
#240
0"
#245
bz V
bz (
bz =
bz >
bz B
bz E
bz Q
bz \
bz d
bz _
b11 `
b0zzzz a
1.
0/
04
b11 P
b100000000000 N
1"
#250
0"
#255
b1011 V
b11011 (
b11011 =
b11011 >
b11011 B
b11011 E
b11011 Q
b11011 \
b11011 d
b1011 T
b1 0
b1 H
b1 R
b1 U
0.
1-
16
b100 P
b110000000 N
1"
#260
0"
#265
b1011 2
b1011 [
b1011 b
b1011 3
b1011 W
b1011 X
b1011 Y
bz1011 (
bz1011 =
bz1011 >
bz1011 B
bz1011 E
bz1011 Q
bz1011 \
bz1011 d
b1011 S
14
0-
06
15
b101 P
b1001000000 N
1"
#270
0"
#275
b1 9
b1 C
b1 F
b1 G
b1 V
b1 (
b1 =
b1 >
b1 B
b1 E
b1 Q
b1 \
b1 d
bz S
04
1-
05
1,
b110 P
b100000010 N
1"
#280
0"
#285
b100100 :
b100100 ?
b100100 A
b100100 @
b100 V
b100100 (
b100100 =
b100100 >
b100100 B
b100100 E
b100100 Q
b100100 \
b100100 d
b100100 D
0-
18
1<
0,
b1 P
b11000 N
1"
#290
0"
#295
b11 _
b11 2
b11 [
b11 b
b11 a
b11 3
b11 W
b11 X
b11 Y
b11 V
bz0011 (
bz0011 =
bz0011 >
bz0011 B
bz0011 E
bz0011 Q
bz0011 \
bz0011 d
1/
14
08
0<
b10 P
b11000000000 N
1"
#300
0"
#305
bz V
bz (
bz =
bz >
bz B
bz E
bz Q
bz \
bz d
bz _
b100 `
b0zzzz a
1.
0/
04
b11 P
b100000000000 N
1"
#310
0"
#315
b1100 V
b101100 (
b101100 =
b101100 >
b101100 B
b101100 E
b101100 Q
b101100 \
b101100 d
b1100 T
b10 0
b10 H
b10 R
b10 U
0.
1-
16
b100 P
b110000000 N
1"
#320
0"
#325
b1100 2
b1100 [
b1100 b
b1100 3
b1100 W
b1100 X
b1100 Y
bz1100 (
bz1100 =
bz1100 >
bz1100 B
bz1100 E
bz1100 Q
bz1100 \
bz1100 d
b1100 S
14
0-
06
15
b101 P
b1001000000 N
1"
#330
0"
#335
b111 9
b111 C
b111 F
b111 G
b111 V
b111 (
b111 =
b111 >
b111 B
b111 E
b111 Q
b111 \
b111 d
bz S
04
1-
05
1,
b110 P
b100000010 N
1"
#340
0"
#345
b11101 :
b11101 ?
b11101 A
b11101 @
b1101 V
b11101 (
b11101 =
b11101 >
b11101 B
b11101 E
b11101 Q
b11101 \
b11101 d
b11101 D
0-
17
18
1<
0,
b1 P
b111000 N
1"
#350
0"
#355
b100 _
b100 2
b100 [
b100 b
b100 a
b100 3
b100 W
b100 X
b100 Y
b100 V
bz0100 (
bz0100 =
bz0100 >
bz0100 B
bz0100 E
bz0100 Q
bz0100 \
bz0100 d
1/
14
07
08
0<
b10 P
b11000000000 N
1"
#360
0"
#365
bz V
bz (
bz =
bz >
bz B
bz E
bz Q
bz \
bz d
bz _
b101 `
b0zzzz a
1.
0/
04
b11 P
b100000000000 N
1"
#370
0"
#375
bx V
b1110xxxx (
b1110xxxx =
b1110xxxx >
b1110xxxx B
b1110xxxx E
b1110xxxx Q
b1110xxxx \
b1110xxxx d
bx T
b1110 0
b1110 H
b1110 R
b1110 U
0.
1-
16
b100 P
b110000000 N
1"
#380
0"
#385
b11101 !
b11101 1
b11101 ]
b11101 ^
b1101 V
b11101 (
b11101 =
b11101 >
b11101 B
b11101 E
b11101 Q
b11101 \
b11101 d
0-
06
1;
1+
b101 P
b101 N
1"
#390
0"
#395
bz V
bz (
bz =
bz >
bz B
bz E
bz Q
bz \
bz d
0;
0+
b110 P
b0 N
1"
#400
0"
#405
b1 P
1"
#410
0"
